pymysqlpro/__init__.py
pymysqlpro/pymysqlpro.py
pymysqlpro-2.0.4.dist-info/METADATA
pymysqlpro-2.0.4.dist-info/WHEEL
pymysqlpro-2.0.4.dist-info/top_level.txt
pymysqlpro-2.0.4.dist-info/RECORD
