Metadata-Version: 2.1
Name: pymysqlpro
Version: 2.0.4
Summary: 对pymysql和sqlalchem模块的简单整合使用
